{
    "background": "beige",
    "shader": "primitive",
    "camera": "main-camera",

    "children": [

        {
            "name": "main-camera",
            "type": "camera",
            "position": [0, 0.1, 1]
        },

        {
            "color": "gray",
            "position": [0, 10, 0],
            "orientation": [0, 0, 0],
            "geometry": {
                "shape": "triangle",
                "size": 0.3
            }
        },

        {
            "color": "blue",
            "orientation": [-90, 0, 0],
            "geometry": {
                "shape": "plane",
                "size": 0.5
            }
        }

    ]
}
